internxt_data/__init__.py
internxt_data/bigQuery.py
internxt_data/charges_schema.py
internxt_data/customer_schema.py
internxt_data/sessions_schema.py
internxt_data/utils.py
internxt_data-0.1.0.dist-info/WHEEL
internxt_data-0.1.0.dist-info/METADATA
internxt_data-0.1.0.dist-info/RECORD
