Metadata-Version: 2.1
Name: internxt-data
Version: 0.1.0
Summary: 
Author: Joan Mora
Author-email: elcorreudejoanmora@gmail.com
Requires-Python: >=3.8,<3.11
Classifier: Programming Language :: Python :: 3
Classifier: Programming Language :: Python :: 3.10
Classifier: Programming Language :: Python :: 3.8
Classifier: Programming Language :: Python :: 3.9
Requires-Dist: google-cloud-bigquery (>=2.34.2,<3.0.0)
Requires-Dist: stripe (>=2.68.0,<3.0.0)
